<annotation>
	<folder />
	<filename>train285.jpg</filename>
	<path>CribHD-T/PascalVOC/train/train285.jpg</path>
	<source>
		<database>roboflow.com</database>
	</source>
	<size>
		<width>640</width>
		<height>640</height>
		<depth>3</depth>
	</size>
	<segmented>0</segmented>
	<object>
		<name>soft-toy</name>
		<pose>Unspecified</pose>
		<truncated>0</truncated>
		<difficult>0</difficult>
		<occluded>0</occluded>
		<bndbox>
			<xmin>81</xmin>
			<xmax>555</xmax>
			<ymin>85</ymin>
			<ymax>559</ymax>
		</bndbox>
		<polygon>
			<x1>383.125</x1>
			<y1>541.121</y1>
			<x2>386.875</x2>
			<y2>536.599</y2>
			<x3>391.875</x3>
			<y3>533.585</y3>
			<x4>396.875</x4>
			<y4>527.555</y4>
			<x5>408.125</x5>
			<y5>527.555</y5>
			<x6>409.375</x6>
			<y6>529.063</y6>
			<x7>414.375</x7>
			<y7>529.063</y7>
			<x8>415.625</x8>
			<y8>530.57</y8>
			<x9>424.375</x9>
			<y9>530.57</y9>
			<x10>425.625</x10>
			<y10>532.077</y10>
			<x11>433.125</x11>
			<y11>533.585</y11>
			<x12>436.875</x12>
			<y12>536.599</y12>
			<x13>439.375</x13>
			<y13>536.599</y13>
			<x14>441.875</x14>
			<y14>539.614</y14>
			<x15>446.875</x15>
			<y15>542.628</y15>
			<x16>453.125</x16>
			<y16>542.628</y16>
			<x17>454.375</x17>
			<y17>544.136</y17>
			<x18>474.375</x18>
			<y18>544.136</y18>
			<x19>475.625</x19>
			<y19>545.643</y19>
			<x20>481.875</x20>
			<y20>545.643</y20>
			<x21>483.125</x21>
			<y21>547.15</y21>
			<x22>503.125</x22>
			<y22>547.15</y22>
			<x23>504.375</x23>
			<y23>545.643</y23>
			<x24>508.125</x24>
			<y24>545.643</y24>
			<x25>513.125</x25>
			<y25>542.628</y25>
			<x26>516.875</x26>
			<y26>542.628</y26>
			<x27>524.375</x27>
			<y27>538.106</y27>
			<x28>531.875</x28>
			<y28>530.57</y28>
			<x29>533.125</x29>
			<y29>530.57</y29>
			<x30>543.75</x30>
			<y30>516.251</y30>
			<x31>545</x31>
			<y31>511.729</y31>
			<x32>547.5</x32>
			<y32>508.714</y32>
			<x33>548.75</x33>
			<y33>502.685</y33>
			<x34>550</x34>
			<y34>501.178</y34>
			<x35>550</x35>
			<y35>498.163</y35>
			<x36>551.25</x36>
			<y36>496.656</y36>
			<x37>551.25</x37>
			<y37>493.641</y37>
			<x38>552.5</x38>
			<y38>492.134</y38>
			<x39>552.5</x39>
			<y39>487.612</y39>
			<x40>553.75</x40>
			<y40>486.105</y40>
			<x41>553.75</x41>
			<y41>454.451</y41>
			<x42>552.5</x42>
			<y42>452.944</y42>
			<x43>552.5</x43>
			<y43>448.422</y43>
			<x44>550</x44>
			<y44>443.9</y44>
			<x45>548.75</x45>
			<y45>434.856</y45>
			<x46>546.25</x46>
			<y46>431.842</y46>
			<x47>545</x47>
			<y47>427.32</y47>
			<x48>537.5</x48>
			<y48>416.769</y48>
			<x49>532.5</x49>
			<y49>404.71</y49>
			<x50>526.875</x50>
			<y50>397.927</y50>
			<x51>525.625</x51>
			<y51>397.927</y51>
			<x52>524.375</x52>
			<y52>394.913</y52>
			<x53>521.875</x53>
			<y53>394.913</y53>
			<x54>518.125</x54>
			<y54>391.898</y54>
			<x55>498.125</x55>
			<y55>391.898</y55>
			<x56>496.25</x56>
			<y56>389.637</y56>
			<x57>496.25</x57>
			<y57>386.623</y57>
			<x58>495</x58>
			<y58>385.115</y58>
			<x59>495</x59>
			<y59>373.057</y59>
			<x60>493.75</x60>
			<y60>371.55</y60>
			<x61>493.75</x61>
			<y61>364.013</y61>
			<x62>492.5</x62>
			<y62>362.506</y62>
			<x63>492.5</x63>
			<y63>357.984</y63>
			<x64>484.375</x64>
			<y64>346.679</y64>
			<x65>483.125</x65>
			<y65>346.679</y65>
			<x66>476.875</x66>
			<y66>340.65</y66>
			<x67>471.875</x67>
			<y67>339.143</y67>
			<x68>470.625</x68>
			<y68>337.635</y68>
			<x69>460.625</x69>
			<y69>336.128</y69>
			<x70>459.375</x70>
			<y70>334.621</y70>
			<x71>455.625</x71>
			<y71>334.621</y71>
			<x72>454.375</x72>
			<y72>333.114</y72>
			<x73>449.375</x73>
			<y73>333.114</y73>
			<x74>444.375</x74>
			<y74>330.099</y74>
			<x75>434.375</x75>
			<y75>328.592</y75>
			<x76>433.125</x76>
			<y76>327.084</y76>
			<x77>430.625</x77>
			<y77>327.084</y77>
			<x78>429.375</x78>
			<y78>325.577</y78>
			<x79>426.875</x79>
			<y79>325.577</y79>
			<x80>425.625</x80>
			<y80>324.07</y80>
			<x81>423.125</x81>
			<y81>324.07</y81>
			<x82>421.875</x82>
			<y82>322.562</y82>
			<x83>419.375</x83>
			<y83>322.562</y83>
			<x84>414.375</x84>
			<y84>319.548</y84>
			<x85>410.625</x85>
			<y85>319.548</y85>
			<x86>405</x86>
			<y86>315.78</y86>
			<x87>405</x87>
			<y87>311.258</y87>
			<x88>408.125</x88>
			<y88>307.489</y88>
			<x89>414.375</x89>
			<y89>304.475</y89>
			<x90>424.375</x90>
			<y90>310.504</y90>
			<x91>428.125</x91>
			<y91>310.504</y91>
			<x92>429.375</x92>
			<y92>312.011</y92>
			<x93>431.875</x93>
			<y93>312.011</y93>
			<x94>433.125</x94>
			<y94>313.519</y94>
			<x95>438.125</x95>
			<y95>313.519</y95>
			<x96>439.375</x96>
			<y96>315.026</y96>
			<x97>444.375</x97>
			<y97>315.026</y97>
			<x98>445.625</x98>
			<y98>316.533</y98>
			<x99>451.875</x99>
			<y99>316.533</y99>
			<x100>453.125</x100>
			<y100>318.041</y100>
			<x101>461.875</x101>
			<y101>318.041</y101>
			<x102>463.125</x102>
			<y102>316.533</y102>
			<x103>469.375</x103>
			<y103>316.533</y103>
			<x104>470.625</x104>
			<y104>315.026</y104>
			<x105>475.625</x105>
			<y105>313.519</y105>
			<x106>478.125</x106>
			<y106>310.504</y106>
			<x107>484.375</x107>
			<y107>307.489</y107>
			<x108>486.875</x108>
			<y108>304.475</y108>
			<x109>491.875</x109>
			<y109>301.46</y109>
			<x110>503.75</x110>
			<y110>285.634</y110>
			<x111>507.5</x111>
			<y111>276.59</y111>
			<x112>510</x112>
			<y112>273.575</y112>
			<x113>510</x113>
			<y113>272.068</y113>
			<x114>512.5</x114>
			<y114>269.053</y114>
			<x115>517.5</x115>
			<y115>258.502</y115>
			<x116>518.75</x116>
			<y116>249.458</y116>
			<x117>520</x117>
			<y117>247.951</y117>
			<x118>520</x118>
			<y118>243.429</y118>
			<x119>521.25</x119>
			<y119>241.922</y119>
			<x120>521.25</x120>
			<y120>235.893</y120>
			<x121>522.5</x121>
			<y121>234.385</y121>
			<x122>522.5</x122>
			<y122>226.849</y122>
			<x123>525</x123>
			<y123>222.327</y123>
			<x124>525</x124>
			<y124>217.805</y124>
			<x125>526.25</x125>
			<y125>216.298</y125>
			<x126>526.25</x126>
			<y126>193.688</y126>
			<x127>525</x127>
			<y127>192.181</y127>
			<x128>525</x128>
			<y128>184.644</y128>
			<x129>521.25</x129>
			<y129>175.601</y129>
			<x130>521.25</x130>
			<y130>172.586</y130>
			<x131>517.5</x131>
			<y131>163.542</y131>
			<x132>517.5</x132>
			<y132>160.528</y132>
			<x133>515</x133>
			<y133>154.498</y133>
			<x134>511.25</x134>
			<y134>149.976</y134>
			<x135>510</x135>
			<y135>145.455</y135>
			<x136>494.375</x136>
			<y136>126.613</y136>
			<x137>491.875</x137>
			<y137>126.613</y137>
			<x138>481.875</x138>
			<y138>119.077</y138>
			<x139>476.875</x139>
			<y139>119.077</y139>
			<x140>475.625</x140>
			<y140>117.569</y140>
			<x141>471.875</x141>
			<y141>117.569</y141>
			<x142>470.625</x142>
			<y142>116.062</y142>
			<x143>466.875</x143>
			<y143>116.062</y143>
			<x144>465.625</x144>
			<y144>114.555</y144>
			<x145>460.625</x145>
			<y145>114.555</y145>
			<x146>454.375</x146>
			<y146>110.033</y146>
			<x147>445.625</x147>
			<y147>110.033</y147>
			<x148>444.375</x148>
			<y148>108.526</y148>
			<x149>434.375</x149>
			<y149>108.526</y149>
			<x150>433.125</x150>
			<y150>110.033</y150>
			<x151>431.875</x151>
			<y151>108.526</y151>
			<x152>424.375</x152>
			<y152>108.526</y152>
			<x153>423.125</x153>
			<y153>110.033</y153>
			<x154>418.125</x154>
			<y154>110.033</y154>
			<x155>416.875</x155>
			<y155>111.54</y155>
			<x156>413.125</x156>
			<y156>111.54</y156>
			<x157>411.875</x157>
			<y157>113.048</y157>
			<x158>404.375</x158>
			<y158>114.555</y158>
			<x159>403.125</x159>
			<y159>116.062</y159>
			<x160>398.125</x160>
			<y160>116.062</y160>
			<x161>389.375</x161>
			<y161>110.033</y161>
			<x162>381.875</x162>
			<y162>102.496</y162>
			<x163>373.125</x163>
			<y163>97.975</y163>
			<x164>370.625</x164>
			<y164>94.96</y164>
			<x165>368.125</x165>
			<y165>94.96</y165>
			<x166>364.375</x166>
			<y166>91.945</y166>
			<x167>361.875</x167>
			<y167>91.945</y167>
			<x168>356.875</x168>
			<y168>88.931</y168>
			<x169>351.875</x169>
			<y169>88.931</y169>
			<x170>350.625</x170>
			<y170>87.423</y170>
			<x171>346.875</x171>
			<y171>87.423</y171>
			<x172>345.625</x172>
			<y172>85.916</y172>
			<x173>338.125</x173>
			<y173>85.916</y173>
			<x174>336.875</x174>
			<y174>84.409</y174>
			<x175>333.125</x175>
			<y175>84.409</y175>
			<x176>331.875</x176>
			<y176>85.916</y176>
			<x177>325.625</x177>
			<y177>85.916</y177>
			<x178>324.375</x178>
			<y178>87.423</y178>
			<x179>319.375</x179>
			<y179>87.423</y179>
			<x180>318.125</x180>
			<y180>88.931</y180>
			<x181>303.125</x181>
			<y181>90.438</y181>
			<x182>298.125</x182>
			<y182>94.96</y182>
			<x183>295.625</x183>
			<y183>94.96</y183>
			<x184>293.125</x184>
			<y184>97.975</y184>
			<x185>278.125</x185>
			<y185>100.989</y185>
			<x186>268.125</x186>
			<y186>108.526</y186>
			<x187>265.625</x187>
			<y187>108.526</y187>
			<x188>261.875</x188>
			<y188>111.54</y188>
			<x189>251.875</x189>
			<y189>114.555</y189>
			<x190>248.125</x190>
			<y190>117.569</y190>
			<x191>245.625</x191>
			<y191>117.569</y191>
			<x192>236.875</x192>
			<y192>123.599</y192>
			<x193>225.625</x193>
			<y193>137.164</y193>
			<x194>224.375</x194>
			<y194>137.164</y194>
			<x195>215.625</x195>
			<y195>147.715</y195>
			<x196>213.125</x196>
			<y196>149.223</y196>
			<x197>201.875</x197>
			<y197>149.223</y197>
			<x198>200.625</x198>
			<y198>147.715</y198>
			<x199>176.875</x199>
			<y199>147.715</y199>
			<x200>175.625</x200>
			<y200>149.223</y200>
			<x201>170.625</x201>
			<y201>149.223</y201>
			<x202>169.375</x202>
			<y202>150.73</y202>
			<x203>163.125</x203>
			<y203>150.73</y203>
			<x204>159.375</x204>
			<y204>153.745</y204>
			<x205>155.625</x205>
			<y205>153.745</y205>
			<x206>146.875</x206>
			<y206>159.774</y206>
			<x207>144.375</x207>
			<y207>159.774</y207>
			<x208>126.875</x208>
			<y208>170.325</y208>
			<x209>123.125</x209>
			<y209>174.847</y209>
			<x210>121.875</x210>
			<y210>174.847</y210>
			<x211>119.375</x211>
			<y211>177.862</y211>
			<x212>118.125</x212>
			<y212>177.862</y212>
			<x213>115.625</x213>
			<y213>180.876</y213>
			<x214>110</x214>
			<y214>184.644</y214>
			<x215>110</x215>
			<y215>186.152</y215>
			<x216>105</x216>
			<y216>192.181</y216>
			<x217>103.75</x217>
			<y217>196.703</y217>
			<x218>97.5</x218>
			<y218>205.747</y218>
			<x219>95</x219>
			<y219>213.283</y219>
			<x220>90</x220>
			<y220>220.82</y220>
			<x221>88.75</x221>
			<y221>228.356</y221>
			<x222>85</x222>
			<y222>234.385</y222>
			<x223>82.5</x223>
			<y223>240.415</y223>
			<x224>82.5</x224>
			<y224>243.429</y224>
			<x225>81.25</x225>
			<y225>244.936</y225>
			<x226>81.25</x226>
			<y226>255.488</y226>
			<x227>80</x227>
			<y227>256.995</y227>
			<x228>80</x228>
			<y228>284.126</y228>
			<x229>81.25</x229>
			<y229>285.634</y229>
			<x230>81.25</x230>
			<y230>291.663</y230>
			<x231>82.5</x231>
			<y231>293.17</y231>
			<x232>82.5</x232>
			<y232>299.199</y232>
			<x233>83.75</x233>
			<y233>300.707</y233>
			<x234>83.75</x234>
			<y234>311.258</y234>
			<x235>87.5</x235>
			<y235>320.301</y235>
			<x236>90</x236>
			<y236>323.316</y236>
			<x237>91.25</x237>
			<y237>327.838</y237>
			<x238>95</x238>
			<y238>332.36</y238>
			<x239>96.25</x239>
			<y239>336.882</y239>
			<x240>108.75</x240>
			<y240>351.955</y240>
			<x241>108.75</x241>
			<y241>353.462</y241>
			<x242>115</x242>
			<y242>360.999</y242>
			<x243>115.625</x243>
			<y243>363.26</y243>
			<x244>116.875</x244>
			<y244>363.26</y244>
			<x245>120.625</x245>
			<y245>367.781</y245>
			<x246>121.875</x246>
			<y246>367.781</y246>
			<x247>125.625</x247>
			<y247>372.303</y247>
			<x248>126.875</x248>
			<y248>372.303</y248>
			<x249>134.375</x249>
			<y249>381.347</y249>
			<x250>140.625</x250>
			<y250>384.362</y250>
			<x251>150.625</x251>
			<y251>393.406</y251>
			<x252>159.375</x252>
			<y252>393.406</y252>
			<x253>160.625</x253>
			<y253>394.913</y253>
			<x254>165.625</x254>
			<y254>394.913</y254>
			<x255>166.875</x255>
			<y255>396.42</y255>
			<x256>173.125</x256>
			<y256>396.42</y256>
			<x257>174.375</x257>
			<y257>394.913</y257>
			<x258>178.125</x258>
			<y258>394.913</y258>
			<x259>181.875</x259>
			<y259>391.898</y259>
			<x260>184.375</x260>
			<y260>391.898</y260>
			<x261>188.125</x261>
			<y261>388.884</y261>
			<x262>190.625</x262>
			<y262>388.884</y262>
			<x263>200.625</x263>
			<y263>379.84</y263>
			<x264>204.375</x264>
			<y264>378.333</y264>
			<x265>208.125</x265>
			<y265>372.303</y265>
			<x266>211.875</x266>
			<y266>370.796</y266>
			<x267>215.625</x267>
			<y267>366.274</y267>
			<x268>219.375</x268>
			<y268>364.767</y268>
			<x269>238.125</x269>
			<y269>343.665</y269>
			<x270>241.875</x270>
			<y270>342.157</y270>
			<x271>246.875</x271>
			<y271>336.128</y271>
			<x272>249.375</x272>
			<y272>337.635</y272>
			<x273>251.25</x273>
			<y273>339.896</y273>
			<x274>231.25</x274>
			<y274>360.999</y274>
			<x275>231.25</x275>
			<y275>362.506</y275>
			<x276>225</x276>
			<y276>370.042</y276>
			<x277>225</x277>
			<y277>371.55</y277>
			<x278>222.5</x278>
			<y278>374.564</y278>
			<x279>217.5</x279>
			<y279>385.115</y279>
			<x280>215</x280>
			<y280>397.174</y280>
			<x281>211.25</x281>
			<y281>404.71</y281>
			<x282>210</x282>
			<y282>413.754</y282>
			<x283>208.75</x283>
			<y283>415.261</y283>
			<x284>208.75</x284>
			<y284>442.393</y284>
			<x285>210</x285>
			<y285>443.9</y285>
			<x286>210</x286>
			<y286>448.422</y286>
			<x287>223.75</x287>
			<y287>466.51</y287>
			<x288>223.75</x288>
			<y288>474.046</y288>
			<x289>225</x289>
			<y289>477.061</y289>
			<x290>226.875</x290>
			<y290>479.322</y290>
			<x291>228.125</x291>
			<y291>477.814</y291>
			<x292>235</x292>
			<y292>478.568</y292>
			<x293>235</x293>
			<y293>486.105</y293>
			<x294>236.25</x294>
			<y294>487.612</y294>
			<x295>237.5</x295>
			<y295>498.163</y295>
			<x296>240</x296>
			<y296>502.685</y296>
			<x297>241.25</x297>
			<y297>508.714</y297>
			<x298>243.75</x298>
			<y298>511.729</y298>
			<x299>248.75</x299>
			<y299>523.787</y299>
			<x300>255</x300>
			<y300>531.324</y300>
			<x301>255</x301>
			<y301>532.831</y301>
			<x302>256.875</x302>
			<y302>533.585</y302>
			<x303>260.625</x303>
			<y303>538.106</y303>
			<x304>265.625</x304>
			<y304>539.614</y304>
			<x305>266.875</x305>
			<y305>541.121</y305>
			<x306>269.375</x306>
			<y306>541.121</y306>
			<x307>270.625</x307>
			<y307>542.628</y307>
			<x308>278.125</x308>
			<y308>542.628</y308>
			<x309>279.375</x309>
			<y309>544.136</y309>
			<x310>281.875</x310>
			<y310>544.136</y310>
			<x311>288.125</x311>
			<y311>550.165</y311>
			<x312>293.125</x312>
			<y312>553.179</y312>
			<x313>295.625</x313>
			<y313>553.179</y313>
			<x314>296.875</x314>
			<y314>554.687</y314>
			<x315>303.125</x315>
			<y315>554.687</y315>
			<x316>304.375</x316>
			<y316>556.194</y316>
			<x317>314.375</x317>
			<y317>556.194</y317>
			<x318>315.625</x318>
			<y318>557.701</y318>
			<x319>318.125</x319>
			<y319>556.194</y319>
			<x320>329.375</x320>
			<y320>556.194</y320>
			<x321>330.625</x321>
			<y321>557.701</y321>
			<x322>338.75</x322>
			<y322>556.948</y322>
			<x323>348.125</x323>
			<y323>556.194</y323>
			<x324>349.375</x324>
			<y324>554.687</y324>
			<x325>355.625</x325>
			<y325>554.687</y325>
			<x326>356.875</x326>
			<y326>553.179</y326>
			<x327>366.875</x327>
			<y327>550.165</y327>
			<x328>370.625</x328>
			<y328>547.15</y328>
			<x329>373.125</x329>
			<y329>547.15</y329>
			<x330>383.125</x330>
			<y330>541.121</y330>
		</polygon>
	</object>
</annotation>